README.rst
setup.py
tree_extractor/__init__.py
tree_extractor/extractor.py
tree_extractor/parser.py
tree_extractor/rules.py
tree_extractor/tests.py
tree_extractor/translator.py
tree_extractor.egg-info/PKG-INFO
tree_extractor.egg-info/SOURCES.txt
tree_extractor.egg-info/dependency_links.txt
tree_extractor.egg-info/requires.txt
tree_extractor.egg-info/top_level.txt