Metadata-Version: 1.1
Name: tree-extractor
Version: 0.1.9
Summary: Lib to extract html elements by preserving ancestors and cleaning CSS
Home-page: https://github.com/jurismarches/tree_extractor
Author: Jurismarchés
Author-email: contact@jurismarches.com
License: UNKNOWN
Platform: UNKNOWN
Classifier: Development Status :: 2 - Pre-Alpha
Classifier: Programming Language :: Python :: 2.6
Classifier: Programming Language :: Python :: 2.7
Classifier: Programming Language :: Python :: 3.1
Classifier: Programming Language :: Python :: 3.2
Classifier: Programming Language :: Python :: 3.3
Classifier: Programming Language :: Python :: 3.4
